README.rst
setup.py
openmacapp/__init__.py
openmacapp.egg-info/PKG-INFO
openmacapp.egg-info/SOURCES.txt
openmacapp.egg-info/dependency_links.txt
openmacapp.egg-info/entry_points.txt
openmacapp.egg-info/requires.txt
openmacapp.egg-info/top_level.txt
openmacapp.egg-info/zip-safe