Metadata-Version: 1.1
Name: openmacapp
Version: 27
Summary: Search and start a mac app from the commandline
Home-page: https://github.com/erikdejonge/openmacapp
Author: Erik de Jonge
Author-email: erik@a8.nl
License: GPL
Platform: UNKNOWN
Classifier: Programming Language :: Python :: 3
Classifier: Development Status :: 4 - Beta 
Classifier: Intended Audience :: Developers
Classifier: License :: OSI Approved :: GNU Library or Lesser General Public License (LGPL)
Classifier: Operating System :: POSIX
Classifier: Environment :: MacOS X
Classifier: Topic :: System
